EasyAuthorization/__init__.py
EasyAuthorization/main.py
EasyAuthorization-0.1.dist-info/METADATA
EasyAuthorization-0.1.dist-info/WHEEL
EasyAuthorization-0.1.dist-info/top_level.txt
EasyAuthorization-0.1.dist-info/RECORD
